{
  "$schema": "https://developer.microsoft.com/json-schemas/fabric/item/report/definition/visualContainer/2.3.0/schema.json",
  "name": "4d319197f3b1a7d1e8f4",
  "position": {
    "x": 423.3448735414251,
    "y": 100.72872929500824,
    "z": 12000,
    "height": 35.595788087364056,
    "width": 81.939923520074373,
    "tabOrder": 9000
  },
  "visual": {
    "visualType": "textbox",
    "objects": {
      "general": [
        {
          "properties": {
            "paragraphs": [
              {
                "textRuns": [
                  {
                    "value": "vs LY %",
                    "textStyle": {
                      "fontSize": "11pt"
                    }
                  }
                ],
                "horizontalTextAlignment": "center"
              }
            ]
          }
        }
      ]
    },
    "visualContainerObjects": {
      "title": [
        {
          "properties": {
            "titleWrap": {
              "expr": {
                "Literal": {
                  "Value": "true"
                }
              }
            }
          }
        }
      ],
      "background": [
        {
          "properties": {
            "show": {
              "expr": {
                "Literal": {
                  "Value": "false"
                }
              }
            },
            "transparency": {
              "expr": {
                "Literal": {
                  "Value": "0D"
                }
              }
            }
          }
        }
      ],
      "general": [
        {
          "properties": {
            "keepLayerOrder": {
              "expr": {
                "Literal": {
                  "Value": "true"
                }
              }
            }
          }
        }
      ],
      "visualHeader": [
        {
          "properties": {
            "show": {
              "expr": {
                "Literal": {
                  "Value": "false"
                }
              }
            }
          }
        }
      ]
    },
    "drillFilterOtherVisuals": true
  }
}