{
  "$schema": "https://developer.microsoft.com/json-schemas/fabric/item/report/definition/page/2.0.0/schema.json",
  "name": "ReportSection1c5466509a06894c919b",
  "displayName": "Trading Margin Inc BIM",
  "displayOption": "FitToPage",
  "height": 720,
  "width": 1280,
  "filterConfig": {
    "filters": [
      {
        "name": "Filter811e75822e6b04da07e8",
        "ordinal": 0,
        "field": {
          "Column": {
            "Expression": {
              "SourceRef": {
                "Entity": "Channels"
              }
            },
            "Property": "Channel"
          }
        },
        "type": "Categorical",
        "howCreated": "User"
      },
      {
        "name": "Filterc15adb77de83905ec95a",
        "ordinal": 1,
        "field": {
          "Column": {
            "Expression": {
              "SourceRef": {
                "Entity": "Channels"
              }
            },
            "Property": "Channel Detail"
          }
        },
        "type": "Categorical",
        "howCreated": "User",
        "objects": {
          "general": [
            {
              "properties": {}
            }
          ]
        }
      },
      {
        "name": "Filterbb06f37f1e2e2668540b",
        "ordinal": 2,
        "field": {
          "Column": {
            "Expression": {
              "SourceRef": {
                "Entity": "Stores"
              }
            },
            "Property": "worldwideHierName"
          }
        },
        "type": "Categorical",
        "filter": {
          "Version": 2,
          "From": [
            {
              "Name": "s",
              "Entity": "Stores",
              "Type": 0
            }
          ],
          "Where": [
            {
              "Condition": {
                "Not": {
                  "Expression": {
                    "In": {
                      "Expressions": [
                        {
                          "Column": {
                            "Expression": {
                              "SourceRef": {
                                "Source": "s"
                              }
                            },
                            "Property": "worldwideHierName"
                          }
                        }
                      ],
                      "Values": [
                        [
                          {
                            "Literal": {
                              "Value": "'International Website'"
                            }
                          }
                        ]
                      ]
                    }
                  }
                }
              }
            }
          ]
        },
        "howCreated": "User",
        "isHiddenInViewMode": true,
        "objects": {
          "general": [
            {
              "properties": {
                "isInvertedSelectionMode": {
                  "expr": {
                    "Literal": {
                      "Value": "true"
                    }
                  }
                }
              }
            }
          ]
        }
      },
      {
        "name": "Filter8d289adcb98635e8ffbb",
        "ordinal": 3,
        "field": {
          "Column": {
            "Expression": {
              "SourceRef": {
                "Entity": "Stores"
              }
            },
            "Property": "partyName"
          }
        },
        "type": "Categorical",
        "filter": {
          "Version": 2,
          "From": [
            {
              "Name": "s",
              "Entity": "Stores",
              "Type": 0
            }
          ],
          "Where": [
            {
              "Condition": {
                "Not": {
                  "Expression": {
                    "In": {
                      "Expressions": [
                        {
                          "Column": {
                            "Expression": {
                              "SourceRef": {
                                "Source": "s"
                              }
                            },
                            "Property": "partyName"
                          }
                        }
                      ],
                      "Values": [
                        [
                          {
                            "Literal": {
                              "Value": "'Ireland'"
                            }
                          }
                        ]
                      ]
                    }
                  }
                }
              }
            }
          ]
        },
        "howCreated": "User",
        "isHiddenInViewMode": true,
        "objects": {
          "general": [
            {
              "properties": {
                "isInvertedSelectionMode": {
                  "expr": {
                    "Literal": {
                      "Value": "true"
                    }
                  }
                }
              }
            }
          ]
        }
      },
      {
        "name": "Filter4fc6eff2d71aeb9237d7",
        "ordinal": 4,
        "field": {
          "Column": {
            "Expression": {
              "SourceRef": {
                "Entity": "MetricMasterPnLNumFormat"
              }
            },
            "Property": "Format"
          }
        },
        "type": "Categorical",
        "filter": {
          "Version": 2,
          "From": [
            {
              "Name": "m",
              "Entity": "MetricMasterPnLNumFormat",
              "Type": 0
            }
          ],
          "Where": [
            {
              "Condition": {
                "In": {
                  "Expressions": [
                    {
                      "Column": {
                        "Expression": {
                          "SourceRef": {
                            "Source": "m"
                          }
                        },
                        "Property": "Format"
                      }
                    }
                  ],
                  "Values": [
                    [
                      {
                        "Literal": {
                          "Value": "'Formatted'"
                        }
                      }
                    ]
                  ]
                }
              }
            }
          ]
        },
        "howCreated": "User",
        "isHiddenInViewMode": true,
        "isLockedInViewMode": true
      },
      {
        "name": "Filter60361c2ae70002e95e57",
        "ordinal": 5,
        "field": {
          "Column": {
            "Expression": {
              "SourceRef": {
                "Entity": "Products"
              }
            },
            "Property": "Dept"
          }
        },
        "type": "Categorical",
        "howCreated": "User"
      },
      {
        "name": "Filterd6db797aac88231ec9d4",
        "ordinal": 6,
        "field": {
          "Column": {
            "Expression": {
              "SourceRef": {
                "Entity": "ComparatorMaster"
              }
            },
            "Property": "Comparator"
          }
        },
        "type": "Categorical",
        "filter": {
          "Version": 2,
          "From": [
            {
              "Name": "c",
              "Entity": "ComparatorMaster",
              "Type": 0
            }
          ],
          "Where": [
            {
              "Condition": {
                "Not": {
                  "Expression": {
                    "In": {
                      "Expressions": [
                        {
                          "Column": {
                            "Expression": {
                              "SourceRef": {
                                "Source": "c"
                              }
                            },
                            "Property": "Comparator"
                          }
                        }
                      ],
                      "Values": [
                        [
                          {
                            "Literal": {
                              "Value": "'FC'"
                            }
                          }
                        ],
                        [
                          {
                            "Literal": {
                              "Value": "'QRF'"
                            }
                          }
                        ]
                      ]
                    }
                  }
                }
              }
            }
          ]
        },
        "howCreated": "User",
        "isHiddenInViewMode": true,
        "objects": {
          "general": [
            {
              "properties": {
                "isInvertedSelectionMode": {
                  "expr": {
                    "Literal": {
                      "Value": "true"
                    }
                  }
                }
              }
            }
          ]
        }
      },
      {
        "name": "Filterc6a17ac4c69b32ab5852",
        "ordinal": 7,
        "field": {
          "Column": {
            "Expression": {
              "SourceRef": {
                "Entity": "Products"
              }
            },
            "Property": "BU"
          }
        },
        "type": "Categorical",
        "filter": {
          "Version": 2,
          "From": [
            {
              "Name": "p",
              "Entity": "Products",
              "Type": 0
            }
          ],
          "Where": [
            {
              "Condition": {
                "Not": {
                  "Expression": {
                    "In": {
                      "Expressions": [
                        {
                          "Column": {
                            "Expression": {
                              "SourceRef": {
                                "Source": "p"
                              }
                            },
                            "Property": "BU"
                          }
                        }
                      ],
                      "Values": [
                        [
                          {
                            "Literal": {
                              "Value": "null"
                            }
                          }
                        ]
                      ]
                    }
                  }
                }
              }
            }
          ]
        },
        "howCreated": "User",
        "isHiddenInViewMode": true,
        "objects": {
          "general": [
            {
              "properties": {
                "isInvertedSelectionMode": {
                  "expr": {
                    "Literal": {
                      "Value": "true"
                    }
                  }
                }
              }
            }
          ]
        }
      }
    ],
    "filterSortOrder": "Custom"
  },
  "objects": {
    "background": [
      {
        "properties": {
          "image": {
            "image": {
              "name": {
                "expr": {
                  "Literal": {
                    "Value": "'pbi_ra_background_narrower_ribbon.png'"
                  }
                }
              },
              "url": {
                "expr": {
                  "ResourcePackageItem": {
                    "PackageName": "RegisteredResources",
                    "PackageType": 1,
                    "ItemName": "pbi_ra_background_narrower_rib9585068097632983.png"
                  }
                }
              },
              "scaling": {
                "expr": {
                  "Literal": {
                    "Value": "'Normal'"
                  }
                }
              }
            }
          },
          "transparency": {
            "expr": {
              "Literal": {
                "Value": "0D"
              }
            }
          }
        }
      }
    ],
    "outspacePane": [
      {
        "properties": {
          "titleSize": {
            "expr": {
              "Literal": {
                "Value": "8L"
              }
            }
          },
          "inputBoxColor": {
            "solid": {
              "color": {
                "expr": {
                  "Literal": {
                    "Value": "'#E6E6E6'"
                  }
                }
              }
            }
          },
          "searchTextSize": {
            "expr": {
              "Literal": {
                "Value": "8L"
              }
            }
          },
          "backgroundColor": {
            "solid": {
              "color": {
                "expr": {
                  "Literal": {
                    "Value": "'#E6E6E6'"
                  }
                }
              }
            }
          }
        }
      }
    ],
    "filterCard": [
      {
        "properties": {
          "foregroundColor": {
            "solid": {
              "color": {
                "expr": {
                  "ThemeDataColor": {
                    "ColorId": 0,
                    "Percent": 0
                  }
                }
              }
            }
          },
          "textSize": {
            "expr": {
              "Literal": {
                "Value": "8L"
              }
            }
          },
          "inputBoxColor": {
            "solid": {
              "color": {
                "expr": {
                  "Literal": {
                    "Value": "'#808080'"
                  }
                }
              }
            }
          },
          "backgroundColor": {
            "solid": {
              "color": {
                "expr": {
                  "Literal": {
                    "Value": "'#B3B3B3'"
                  }
                }
              }
            }
          }
        },
        "selector": {
          "id": "Available"
        }
      },
      {
        "properties": {
          "foregroundColor": {
            "solid": {
              "color": {
                "expr": {
                  "ThemeDataColor": {
                    "ColorId": 0,
                    "Percent": 0
                  }
                }
              }
            }
          },
          "textSize": {
            "expr": {
              "Literal": {
                "Value": "8L"
              }
            }
          },
          "inputBoxColor": {
            "solid": {
              "color": {
                "expr": {
                  "Literal": {
                    "Value": "'#808080'"
                  }
                }
              }
            }
          },
          "backgroundColor": {
            "solid": {
              "color": {
                "expr": {
                  "Literal": {
                    "Value": "'#333333'"
                  }
                }
              }
            }
          }
        },
        "selector": {
          "id": "Applied"
        }
      }
    ]
  },
  "visibility": "HiddenInViewMode",
  "visualInteractions": [
    {
      "source": "c5214bbe8794a90eaa5c",
      "target": "1626055fa603a1b291e4",
      "type": "NoFilter"
    },
    {
      "source": "6e3728299ee572ae73c8",
      "target": "7d7ee991860606b426bc",
      "type": "NoFilter"
    },
    {
      "source": "7d7ee991860606b426bc",
      "target": "6e3728299ee572ae73c8",
      "type": "NoFilter"
    },
    {
      "source": "6e3728299ee572ae73c8",
      "target": "1626055fa603a1b291e4",
      "type": "NoFilter"
    },
    {
      "source": "7d7ee991860606b426bc",
      "target": "9e26ffbe0329788b53d4",
      "type": "NoFilter"
    },
    {
      "source": "f53dbf50bd23eaab81c1",
      "target": "fe7153d958b50a032130",
      "type": "NoFilter"
    },
    {
      "source": "7d7ee991860606b426bc",
      "target": "fe7153d958b50a032130",
      "type": "NoFilter"
    },
    {
      "source": "6e3728299ee572ae73c8",
      "target": "fe7153d958b50a032130",
      "type": "NoFilter"
    }
  ]
}