{
  "$schema": "https://developer.microsoft.com/json-schemas/fabric/item/report/definition/visualContainer/2.3.0/schema.json",
  "name": "6956c2fd7023ddae0990",
  "position": {
    "x": 858.86122487142234,
    "y": 444.89796091833875,
    "z": 26000,
    "height": 27,
    "width": 207.14285714285714,
    "tabOrder": 26000
  },
  "visual": {
    "visualType": "textbox",
    "objects": {
      "general": [
        {
          "properties": {
            "paragraphs": [
              {
                "textRuns": [
                  {
                    "value": "Home & Beauty",
                    "textStyle": {
                      "fontSize": "10pt"
                    }
                  }
                ],
                "horizontalTextAlignment": "center"
              }
            ]
          }
        }
      ]
    },
    "visualContainerObjects": {
      "border": [
        {
          "properties": {
            "show": {
              "expr": {
                "Literal": {
                  "Value": "false"
                }
              }
            },
            "color": {
              "solid": {
                "color": {
                  "expr": {
                    "ThemeDataColor": {
                      "ColorId": 0,
                      "Percent": -0.2
                    }
                  }
                }
              }
            }
          }
        }
      ]
    },
    "drillFilterOtherVisuals": true
  }
}